Metadata-Version: 1.1
Name: search-console
Version: 0.1.1
Summary: A Python Programmable interface to manage search engine consoles.
Home-page: https://github.com/biwin/search-console
Author: Biwin John Joseph
Author-email: biwinjohn@gmail.com
License: UNKNOWN
Download-URL: https://github.com/biwin/search-console
Keywords: search console,webmaster,seo,python
Platform: UNKNOWN
